<annotation verified="yes">
	<folder>all</folder>
	<filename>71. clinical-trials-francoise-pause-during-trial-wandercraft-e1528749177214.jpg</filename>
	<path>/home/joao/Projects/computer-vision-tests/tensorflow/custom_object_detection/workspace/training_demo/images/all/71. clinical-trials-francoise-pause-during-trial-wandercraft-e1528749177214.jpg</path>
	<source>
		<database>Unknown</database>
	</source>
	<size>
		<width>640</width>
		<height>474</height>
		<depth>3</depth>
	</size>
	<segmented>0</segmented>
	<object>
		<name>feet</name>
		<pose>Unspecified</pose>
		<truncated>0</truncated>
		<difficult>0</difficult>
		<bndbox>
			<xmin>249</xmin>
			<ymin>356</ymin>
			<xmax>322</xmax>
			<ymax>417</ymax>
		</bndbox>
	</object>
	<object>
		<name>feet</name>
		<pose>Unspecified</pose>
		<truncated>0</truncated>
		<difficult>0</difficult>
		<bndbox>
			<xmin>322</xmin>
			<ymin>378</ymin>
			<xmax>392</xmax>
			<ymax>453</ymax>
		</bndbox>
	</object>
	<object>
		<name>feet</name>
		<pose>Unspecified</pose>
		<truncated>0</truncated>
		<difficult>0</difficult>
		<bndbox>
			<xmin>451</xmin>
			<ymin>353</ymin>
			<xmax>508</xmax>
			<ymax>417</ymax>
		</bndbox>
	</object>
	<object>
		<name>feet</name>
		<pose>Unspecified</pose>
		<truncated>1</truncated>
		<difficult>0</difficult>
		<bndbox>
			<xmin>475</xmin>
			<ymin>389</ymin>
			<xmax>593</xmax>
			<ymax>474</ymax>
		</bndbox>
	</object>
	<object>
		<name>feet</name>
		<pose>Unspecified</pose>
		<truncated>1</truncated>
		<difficult>0</difficult>
		<bndbox>
			<xmin>156</xmin>
			<ymin>448</ymin>
			<xmax>251</xmax>
			<ymax>474</ymax>
		</bndbox>
	</object>
	<object>
		<name>feet</name>
		<pose>Unspecified</pose>
		<truncated>1</truncated>
		<difficult>0</difficult>
		<bndbox>
			<xmin>1</xmin>
			<ymin>405</ymin>
			<xmax>111</xmax>
			<ymax>471</ymax>
		</bndbox>
	</object>
	<object>
		<name>feet</name>
		<pose>Unspecified</pose>
		<truncated>0</truncated>
		<difficult>0</difficult>
		<bndbox>
			<xmin>512</xmin>
			<ymin>341</ymin>
			<xmax>601</xmax>
			<ymax>377</ymax>
		</bndbox>
	</object>
</annotation>
